{"ch01.md":"CE1DAQ4g","ch02.md":"CDhswmj1","ch03.md":"CF_UE8jw","ch04.md":"BKDYnnh5","ch05.md":"DSTjHI0g","ch06.md":"S2Y7vqMx","ch07.md":"CW4mMBIV","ch08.md":"DATZQpZ5","ch09.md":"CoNmjx-R","ch10.md":"34n9G1tj","ch11.md":"CPeBLWKg","ch12.md":"bSpEaoQt","ch13.md":"DCJVy6lq","ch14.md":"D7F9E1FS","ch15.md":"XsdsXJY5","ch16.md":"C3mRRHjD","ch17.md":"DpxKfXf7","ch18.md":"CaguQ8vp","ch19.md":"D_SAisIC","ch20.md":"CUwTr9ek","ch21.md":"CdrXQAEv","index.md":"CtuIG1Pm","preface.md":"DCqE1pKK","summary.md":"GGfiDv66"}
