{"ch01.md":"CjCZHvLm","ch02.md":"BwoH1jkf","ch03.md":"D0B_QkgV","ch04.md":"BJk1bDvr","ch05.md":"B5hWJw4s","ch06.md":"kY2hllu9","ch07.md":"DBomjAyK","ch08.md":"DLnBP2Fn","ch09.md":"X5ZwHGBI","ch10.md":"BXltFWeo","ch11.md":"jfHYe2r7","ch12.md":"q1G5jbzM","ch13.md":"DBhvJdtK","ch14.md":"DoLputvB","ch15.md":"DpcpAA96","ch16.md":"DD7Hwd2w","ch17.md":"C5arqZ_v","ch18.md":"DaK_GtVi","ch19.md":"CqL5qkoY","ch20.md":"CSJxQmO1","ch21.md":"n6DNMi68","index.md":"CpLuXLzf","preface.md":"BACwSUUe","summary.md":"BhkF5Ro8"}
